llama_index/program/openai/__init__.py
llama_index/program/openai/base.py
llama_index/program/openai/utils.py
basejump_llama_index_program_openai-0.3.1.post1.dist-info/METADATA
basejump_llama_index_program_openai-0.3.1.post1.dist-info/WHEEL
basejump_llama_index_program_openai-0.3.1.post1.dist-info/licenses/LICENSE
basejump_llama_index_program_openai-0.3.1.post1.dist-info/RECORD
