Metadata-Version: 2.4
Name: basejump-llama-index-program-openai
Version: 0.3.1.post1
Summary: llama-index program openai integration
Author-email: Your Name <you@example.com>
License-Expression: MIT
License-File: LICENSE
Requires-Python: <4.0,>=3.9
Requires-Dist: basejump-llama-index-agent-openai<0.5,>=0.4.0
Requires-Dist: basejump-llama-index-core<0.13,>=0.12.0
Requires-Dist: basejump-llama-index-llms-openai<0.4,>=0.3.0
